clicker/__init__.py
clicker/cli.py
clicker/worker.py
click_worker-0.0.1.dist-info/METADATA
click_worker-0.0.1.dist-info/WHEEL
click_worker-0.0.1.dist-info/entry_points.txt
click_worker-0.0.1.dist-info/top_level.txt
click_worker-0.0.1.dist-info/RECORD
